cocotb_coverage/__init__.py
cocotb_coverage/coverage.py
cocotb_coverage/crv.py
cocotb_coverage-2.0.dist-info/licenses/LICENSE
cocotb_coverage-2.0.dist-info/METADATA
cocotb_coverage-2.0.dist-info/WHEEL
cocotb_coverage-2.0.dist-info/top_level.txt
cocotb_coverage-2.0.dist-info/RECORD
