Metadata-Version: 2.4
Name: cocotb-coverage
Version: 2.0
Summary: Functional Coverage and Constrained Randomization Extensions for Cocotb
Home-page: https://github.com/mciepluc/cocotb-coverage
Author: Marek Cieplucha
Author-email: 
License: BSD
Platform: any
Classifier: Programming Language :: Python :: 3
Classifier: License :: OSI Approved :: BSD License
Classifier: Topic :: Scientific/Engineering :: Electronic Design Automation (EDA)
Requires-Python: >=3.11
License-File: LICENSE
Requires-Dist: cocotb>=2.0
Requires-Dist: python-constraint
Requires-Dist: pyyaml
Dynamic: author
Dynamic: classifier
Dynamic: description
Dynamic: description-content-type
Dynamic: home-page
Dynamic: license
Dynamic: license-file
Dynamic: platform
Dynamic: requires-dist
Dynamic: requires-python
Dynamic: summary
